archive_to_images/__init__.py
archive_to_images/__main__.py
archive_to_images/processor.py
archive_to_images/restorer.py
archive_to_images/transformer.py
archive_to_images-1.0.0.dist-info/LICENSE
archive_to_images-1.0.0.dist-info/METADATA
archive_to_images-1.0.0.dist-info/WHEEL
archive_to_images-1.0.0.dist-info/entry_points.txt
archive_to_images-1.0.0.dist-info/RECORD
