Metadata-Version: 2.1
Name: archive-to-images
Version: 1.0.0
Summary: Archive-To-Images is a Python CLI to transform archives into images and reverse.
Home-page: https://github.com/Peco602/archive-to-images
License: MIT
Author: Giovanni Pecoraro
Author-email: giovanni1.pecoraro@protonmail.com
Requires-Python: >=3.8,<4.0
Classifier: Development Status :: 3 - Alpha
Classifier: Intended Audience :: Developers
Classifier: License :: OSI Approved :: MIT License
Classifier: Operating System :: OS Independent
Classifier: Programming Language :: Python :: 3
Classifier: Programming Language :: Python :: 3.8
Classifier: Programming Language :: Python :: 3.9
Classifier: Programming Language :: Python :: 3.10
Classifier: Programming Language :: Python :: 3.11
Classifier: Programming Language :: Python :: 3
Classifier: Programming Language :: Python :: 3.8
Classifier: Programming Language :: Python :: 3.9
Classifier: Topic :: Software Development :: Libraries :: Python Modules
Requires-Dist: Pillow (==9.3.0)
Requires-Dist: importlib_metadata (>=4.5.0,<5.0.0) ; python_version < "3.8"
Requires-Dist: pyzipper (==0.3.6)
Requires-Dist: rich (>=12.6.0,<13.0.0)
Requires-Dist: typer[all] (>=0.7.0,<0.8.0)
Project-URL: Repository, https://github.com/Peco602/archive-to-images
